ft4ftir/__init__.py
ft4ftir/apodization.py
ft4ftir/fourier_transform.py
ft4ftir/ft.py
ft4ftir/interferogram.py
ft4ftir/test.py
ft4ftir/io/__init__.py
ft4ftir/io/bruker_opus.py
ft4ftirs-0.1.0.dist-info/LICENSE
ft4ftirs-0.1.0.dist-info/METADATA
ft4ftirs-0.1.0.dist-info/WHEEL
ft4ftirs-0.1.0.dist-info/top_level.txt
ft4ftirs-0.1.0.dist-info/RECORD
